Workbook

Sheet Guidance
A1: Contents
A2: BFI and Film4 Future Takes: Production Budget - Guidance
A3: Please read the guidance below in full while putting together an application to BFI and Film4 Future Takes.
A4: Contents
E6: Information & Finance Plan | G6: =A41 -> Budget Breakdown | I6: =A87 -> Access Budget
E7: =D24 -> Project & Team Information | G7: =D46 -> Completing the budget | I7: =D92 -> Updating the access budget
E8: =D31 -> Finance Plan | G8: =D50 -> Additional support | I8: =D96 -> Example costs
E9: =D35 -> In kind support | G9: =D55 -> London Living Wage
G10: =D59 -> Student Placements
G11: =D64 -> Above the line / core team fees
G12: =D67 -> Flat rates
G13: =D71 -> Deliverables
G14: =D75 -> Legal Fees
G15: =D79 -> Insurance
G16: =D82 -> Contingency
A19: Information & Finance Plan
C21: In this section of the Production Budget producers should add information on their proposed production schedule, the names of the core creative team members and the finance plan for the project. Any additional finance and in kind support that has been offered or is planned to be secured should also be included.
D24: Project & Team Information
E25: ▪ Project Title | I25: ▪ Length of project preparation | XX weeks
E26: ▪ Production Company | I26: ▪ Length of shoot | X days
E27: ▪ Producer(s) name | I27: ▪ Length of shooting days | X hours
E28: ▪ Writer(s) name | I28: ▪ Shooting format | Digital, 35mm film or other formats
E29: ▪ Director(s) name
D31: Finance Plan
E32: Award request amount | The total amount being applied for
E33: Any other sources of income | Your project should be fully funded through Future Takes. We will not support projects where the budget exceeds what you are requesting from us (unless you plan to use your own private funds). This may include private equity or investments. Producers do not have to raise additional finance for their project, if it can be made with the amount of funding requested from BFI and Film4 Future Takes. Any contribution of less than £50 should be credited to the contingency of the project.
D35: In kind support
E36: Applicants may find that some kit or post-production houses with whom they have an existing professional relationship will be willing to provide services in kind. We can only allow in-kind work from companies who will be paying their staff directly - individual freelancers cannot work on a BFI and Film4 Future Takes funded film without payment.
E37: Add the organisation/company name and the total amount of the support provided in the finance section of the sheet. Applicants still need to complete the corresponding line on the budget with a cost of £0 and add 'in kind support' in the Notes column for reference.
A41: Budget Breakdown
C43: In this section applicants need to detail all of the costs that they would need to budget for to deliver their project. Producers are not required to put a cost against every line of the budget template – not all cost types will be relevant to a project – and this should only show the expenditure that is actually expected to be incurred.
D46: Completing the budget
E47: Enter information into the yellow cells on the Production Budget tab and the sheet will calculate out the totals. There is space next to every budget line to add notes, this can be information on support in kind, higher than average predicted costs or anything else relevant to include.
E48: There is a breakdown of what the BFI require within the budget in section 4. What you can use the funding for in the funding guidelines.
D50: Additional support
E51: Applicants can get help if they need support to apply for funding. They might need support because they are disabled, neurodivergent or another reason. We work with TAPE Community Film and Music to provide access support. TAPE is an award-winning, community arts charity based in North Wales
E52: Get access support to apply for BFI funds | https://www.bfi.org.uk/get-funding-support/get-access-support-apply-bfi-funds
D55: London Living Wage
E56: All cast and crew involved in the making of a BFI and Film4 Future Takes funded film must be paid at least equivalent to the London Living Wage. Crew fees should have parity across departments. This means that we expect crew members at a similar experience level to be paid the same across the production, for example a Production Assistant would be paid the same as a Camera Assistant. We want to ensure that everyone who works on BFI nd Film4 Future Takes funded productions are paid for their time.
E57: Current Hourly Rate | https://www.london.gov.uk/programmes-strategies/business-and-economy/london-living-wage/
D59: Student Placements
E60: There are very limited exemptions to the London Living Wage rule. We can make an exception for Film and Media students who have a letter from a lecturer or course leader at their college or university, stating that their participation in the production is part of their course. If an application is approved and the producer intends to include student trainees in their crew, they must discuss this with their BFI Executive as early as possible during contracting as they will need to approve this decision.
E61: We will need a letter or other correspondence from the educational institution involved (college or university) confirming that the named student will be working on the named short project in the context of their Film/Media/Animation/Art related course. All team members must be over 18, including student trainees.
D64: Above the line / core team fees
E65: All applications must include a fee for the film’s producer(s), director(s) and writer(s). If a project has a writer/director, only one set of fees needs to be included for both roles.
D67: Flat rates
E68: Certain Heads of Department, like the DOP, Composer and Editor, may prefer to set a flat rate for their work on the project. These fees cannot be waived. Applicants may also negotiate a flat-rate deal with a post house who they have worked with before on other projects. It is up to the post house in question to provide producers with a quote.
E69: Film equipment should be budgeted for outside of HOD fees. If HODs are bringing their own equipment then this should be costed separately in the budget.
D71: Deliverables
E72: All the necessary film deliverables that are outlined in our BFI and Film4 Future Takes Guidelines must be budgeted for. This includes the creation of a DCP, the enhanced access materials for the film and the files required by the BFI National Archive. We advise approaching a number of service providers to get quotes for deliverables costs so productions are budgeted accurately. If an application is successful, a BFI Executive may be able to provide further guidance on service providers.
E73: Deliverables List |
D75: Legal Fees
E76: We require adequate external legal fees to be included for the production. We recommend that your budget includes £5,000 fees for external lawyers. BFI and Film4 can, on request, supply template clearance documents for the selected films (writer, director, individual producer, cast, crew, locations, music composer). If your project involves adaptation of underlying material, it is particularly important to ensure you have allowed adequate costs in your budget to acquire the rights to adapt such material, and for associated legal document(s)
E77: We will try to guide applicants where we can, but we cannot provide legal advice or act on their behalf (e.g. when dealing with agents or negotiating finance terms).
D79: Insurance
E80: Applicants must budget for insurance for the short film to include all customary production insurances (including errors and omissions) on which the BFI and Film4 will require to be added as a loss payee (for production insurance) and as an additional insured (for errors and omissions). The insurance should be in the name of the company or lead producer who owns the rights in the short.
D82: Contingency
E83: Contingency must be a minium of 10% of the total budget. This is to ensure the budget can cover any unexpected costs which arise during the production of the film. A running total of the minimum contingency is provided at the bottom of the sheet. If awarded funding, producers must seek permission from the BFI Executive before spending any contingency.
A87: Access Budget
C89: We’re committed to making our funds as open and inclusive as possible. If any members of the core team, cast and/or crew have access needs that mean there will be additional costs during the production of the project, they can be included these in this part of the document. Access costs can't be speculative - they must relate to specific expenses for specific members of the crew or cast.
D92: Updating the access budget
E93: We do not expect teams to have a full cast or crew in place when applying for funding. If a project is recommended for support we will require an updated budget ahead of contracting. This should include any applicable access costs for any cast or crew that have joined the project since the initial application. If the applications is already seeking the maximum award amount and it has not been possible to cover access costs within that, the producer can apply for these in addition to the maximum award amount.
E94: Including additional access costs will not have a negative impact on an application assessment.
D96: Example costs
E97: People may have different access needs depending on their role and the production. Not all costs can be covered, for example we cannot currently cover childcare expenses. Some of the costs we have seen on previous Shorts include:
E98: ▪ A BSL interpreter to work with members of cast or crew
E99: ▪ Additional transport or accommodation costs for disabled team members
E100: ▪ A fee for the personal assistant of a team member who requires assistance during the production
E101: If someone requires additional shooting time as part of their access request, the associated costs should be included on the appropriate line in the access budget.

Sheet Production Budget
B1: BFI and Film4 Future Takes Budget Template
B3: Project & Team Information | F3: Budget Breakdown | M3: Cost reporting
B4: Project title: | F4: Line No. | G4: Description | H4: Amounts | I4: Unit | J4: Rate (£) | K4: Subtotal | L4: Notes | M4: Actual | N4: Variance | O4: Notes
F5: Example: | H5: 5 | I5: Days | J5: 500 | K5: =H5*J5 -> 2500
B6: Production company: | F6: 1 | G6: Story and script
F7: 1.1 | G7: Writers fee | K7: =J7*H7 -> 0 | N7: =K7-M7 -> 0
B8: Producer(s): | F8: 1.2 | G8: Story rights/options | K8: =J8*H8 -> 0 | N8: =K8-M8 -> 0
B10: Writer(s): | F10: Subtotal: | K10: =SUM(K7:K9) -> 0 | M10: =SUM(M7:M9) -> 0 | N10: =SUM(N7:N9) -> 0
F11: 2 | G11: Producer
B12: Director(s): | F12: 2.1 | G12: Producer fee | K12: =H12*J12 -> 0 | N12: =K12-M12 -> 0
F13: 2.2 | G13: Executive Producers Fee | K13: =H13*J13 -> 0 | N13: =K13-M13 -> 0
B14: Length of preperation:
F15: Subtotal: | K15: =SUM(K12:K14) -> 0 | M15: =SUM(M12:M14) -> 0 | N15: =SUM(N12:N14) -> 0
B16: Length of shoot: | F16: 3 | G16: Director
F17: 3.1 | G17: Director fee | K17: =H17*J17 -> 0 | N17: =K17-M17 -> 0
B18: Length of shoot day:
F19: Subtotal: | K19: =SUM(K17:K18) -> 0 | M19: =SUM(M17:M18) -> 0 | N19: =SUM(N17:N18) -> 0
B20: Shoot format: | F20: Total above the line: | L20: =K10+K15+K19 -> 0 | M20: =SUM(M10,M15,M19) -> 0 | N20: =SUM(N19,N10,N15) -> 0
B22: Finance Plan | F22: 4 | G22: Cast
B23: Source | C23: Amount (£) | D23: Secured | F23: 4.1 | G23: Casting director | K23: =H23*J23 -> 0 | N23: =K23-M23 -> 0
B24: Award Request Amount | F24: 4.2 | G24: Lead cast
F25: 4.2.1 | G25: Lead actor / Voice over artist | K25: =H25*J25 -> 0 | N25: =K25-M25 -> 0
B26: [e.g. Private investment] | D26: [yes/no] | F26: 4.2.2 | G26: Lead actor 2 | K26: =H26*J26 -> 0 | N26: =K26-M26 -> 0
F27: 4.2.3 | G27: Lead actor 3 | K27: =H27*J27 -> 0 | N27: =K27-M27 -> 0
D28: [yes/no] | F28: 4.3 | G28: Supporting cast
F29: 4.3.1 | G29: Supporting actor 1 | K29: =H29*J29 -> 0 | N29: =K29-M29 -> 0
C30: 0 | D30: [yes/no] | F30: 4.3.2 | G30: Supporting actor 2 | K30: =H30*J30 -> 0 | N30: =K30-M30 -> 0
F31: 4.3.3 | G31: Supporting actor 3 | K31: =H31*J31 -> 0 | N31: =K31-M31 -> 0
C32: 0 | D32: [yes/no] | F32: 4.4 | G32: Extras
F33: 4.4.1 | G33: Scene number: | K33: =H33*J33 -> 0 | N33: =K33-M33 -> 0
B34: Total finance plan | C34: =SUM(C24:C33) -> 0 | F34: 4.4.2 | G34: Scene number: | K34: =H34*J34 -> 0 | N34: =K34-M34 -> 0
F35: 4.4.3 | G35: Scene number: | K35: =H35*J35 -> 0 | N35: =K35-M35 -> 0
B36: Total project budget | C36: =J214 -> 0 | F36: 4.5 | G36: Stunt coordinator | K36: =H36*J36 -> 0 | N36: =K36-M36 -> 0
F37: 4.6 | G37: Dialogue coach | K37: =H37*J37 -> 0 | N37: =K37-M37 -> 0
B38: Budget surplus/deficit | C38: =-(C36-C34) -> 0 | F38: 4.7 | G38: Chaperone | K38: =H38*J38 -> 0 | N38: =K38-M38 -> 0
B40: In kind support | F40: Subtotal: | K40: =SUM(K23:K39) -> 0 | M40: =SUM(M23:M39) -> 0 | N40: =SUM(N23:N39) -> 0
B41: Source | C41: Amount (£) | D41: Secured | F41: 5 | G41: Production
B42: [Organisation Name] | C42: 0 | D42: [yes/no] | F42: 5.1 | G42: Line producer | K42: =H42*J42 -> 0 | N42: =K42-M42 -> 0
F43: 5.2 | G43: Production manager | K43: =H43*J43 -> 0 | N43: =K43-M43 -> 0
C44: 0 | D44: [yes/no] | F44: 5.3 | G44: Production coordinator | K44: =H44*J44 -> 0 | N44: =K44-M44 -> 0
F45: 5.4 | G45: Production assistant | K45: =H45*J45 -> 0 | N45: =K45-M45 -> 0
C46: 0 | D46: [yes/no] | F46: 5.5 | G46: Production runner | K46: =H46*J46 -> 0 | N46: =K46-M46 -> 0
F47: 5.6 | G47: Location manager | K47: =H47*J47 -> 0 | N47: =K47-M47 -> 0
B48: Total in kind support | C48: =SUM(C42:C47) -> 0 | F48: 5.7 | G48: Script supervisor | K48: =H48*J48 -> 0 | N48: =K48-M48 -> 0
F50: Subtotal: | K50: =SUM(K42:K49) -> 0 | M50: =SUM(M42:M49) -> 0 | N50: =SUM(N42:N49) -> 0
F51: 6 | G51: Assistant Directors
F52: 6.1 | G52: First assistant director | K52: =H52*J52 -> 0 | N52: =K52-M52 -> 0
F53: 6.2 | G53: Second assistant director | K53: =H53*J53 -> 0 | N53: =K53-M53 -> 0
F54: 6.3 | G54: Third assistant director | K54: =H54*J54 -> 0 | N54: =K54-M54 -> 0
F55: 6.4 | G55: Floor runner 1 | K55: =H55*J55 -> 0 | N55: =K55-M55 -> 0
F56: 6.5 | G56: Floor runner 2 | K56: =H56*J56 -> 0 | N56: =K56-M56 -> 0
F58: Subtotal: | K58: =SUM(K52:K57) -> 0 | M58: =SUM(M52:M57) -> 0 | N58: =SUM(N52:N57) -> 0
F59: 7 | G59: Camera
F60: 7.1 | G60: Director of photography | K60: =H60*J60 -> 0 | N60: =K60-M60 -> 0
F61: 7.2 | G61: First assistant camera | K61: =H61*J61 -> 0 | N61: =K61-M61 -> 0
F62: 7.3 | G62: Second assistant camera | K62: =H62*J62 -> 0 | N62: =K62-M62 -> 0
F63: 7.4 | G63: Grip | K63: =H63*J63 -> 0 | N63: =K63-M63 -> 0
F64: 7.5 | G64: Digital imaging technician | K64: =H64*J64 -> 0 | N64: =K64-M64 -> 0
F65: 7.6 | G65: Camera package | K65: =H65*J65 -> 0 | N65: =K65-M65 -> 0
F66: 7.7 | G66: Hard drives | K66: =H66*J66 -> 0 | N66: =K66-M66 -> 0
F68: Subtotal: | K68: =SUM(K60:K67) -> 0 | M68: =SUM(M60:M67) -> 0 | N68: =SUM(N60:N67) -> 0
F69: 8 | G69: Lighting
F70: 8.1 | G70: Gaffer | K70: =H70*J70 -> 0 | N70: =K70-M70 -> 0
F71: 8.2 | G71: Electrician 1 | K71: =H71*J71 -> 0 | N71: =K71-M71 -> 0
F72: 8.3 | G72: Electrician 2 | K72: =H72*J72 -> 0 | N72: =K72-M72 -> 0
F73: 8.4 | G73: Electrician 3 | K73: =H73*J73 -> 0 | N73: =K73-M73 -> 0
F74: 8.5 | G74: Lighting package | K74: =H74*J74 -> 0 | N74: =K74-M74 -> 0
F75: 8.6 | G75: Purchases | K75: =H75*J75 -> 0 | N75: =K75-M75 -> 0
F76: 8.7 | G76: Generator | K76: =H76*J76 -> 0 | N76: =K76-M76 -> 0
F77: 8.8 | G77: Consumables | K77: =H77*J77 -> 0 | N77: =K77-M77 -> 0
F79: Subtotal: | K79: =SUM(K70:K78) -> 0 | M79: =SUM(M70:M78) -> 0 | N79: =SUM(N70:N78) -> 0
F80: 9 | G80: Sound
F81: 9.1 | G81: Recordist/mixer | K81: =H81*J81 -> 0 | N81: =K81-M81 -> 0
F82: 9.2 | G82: Boom operator | K82: =H82*J82 -> 0 | N82: =K82-M82 -> 0
F83: 9.3 | G83: Sound package | K83: =H83*J83 -> 0 | N83: =K83-M83 -> 0
F84: 9.4 | G84: Radios | K84: =H84*J84 -> 0 | N84: =K84-M84 -> 0
F86: Subtotal: | K86: =SUM(K81:K85) -> 0 | M86: =SUM(M81:M85) -> 0 | N86: =SUM(N81:N85) -> 0
F87: 10 | G87: Production design
F88: 10.1 | G88: Production designer | K88: =H88*J88 -> 0 | N88: =K88-M88 -> 0
F89: 10.2 | G89: Art director | K89: =H89*J89 -> 0 | N89: =K89-M89 -> 0
F90: 10.3 | G90: Set decorator | K90: =H90*J90 -> 0 | N90: =K90-M90 -> 0
F91: 10.4 | G91: Art department assistant | K91: =H91*J91 -> 0 | N91: =K91-M91 -> 0
F92: 10.5 | G92: Standby art director | K92: =H92*J92 -> 0 | N92: =K92-M92 -> 0
F93: 10.6 | G93: Storyboard artist | K93: =H93*J93 -> 0 | N93: =K93-M93 -> 0
F94: 10.7 | G94: Prop master | K94: =H94*J94 -> 0 | N94: =K94-M94 -> 0
F95: 10.8 | G95: Rentals | K95: =H95*J95 -> 0 | N95: =K95-M95 -> 0
F96: 10.9 | G96: Construction | K96: =H96*J96 -> 0 | N96: =K96-M96 -> 0
F97: 10.1 | G97: Special effects supervisor | K97: =H97*J97 -> 0 | N97: =K97-M97 -> 0
F98: 10.11 | G98: Consumbables | K98: =H98*J98 -> 0 | N98: =K98-M98 -> 0
F99: 10.12 | G99: Animals/wrangler | K99: =H99*J99 -> 0 | N99: =K99-M99 -> 0
F100: 10.13 | G100: Action vehicles | K100: =H100*J100 -> 0 | N100: =K100-M100 -> 0
F102: Subtotal: | K102: =SUM(K88:K101) -> 0 | M102: =SUM(M88:M101) -> 0 | N102: =SUM(N88:N101) -> 0
F103: 11 | G103: Costume
F104: 11.1 | G104: Costume designer | K104: =H104*J104 -> 0 | N104: =K104-M104 -> 0
F105: 11.2 | G105: Costume supervisor | K105: =H105*J105 -> 0 | N105: =K105-M105 -> 0
F106: 11.3 | G106: Purchases | K106: =H106*J106 -> 0 | N106: =K106-M106 -> 0
F108: Subtotal: | K108: =SUM(K104:K107) -> 0 | M108: =SUM(M104:M107) -> 0 | N108: =SUM(N104:N107) -> 0
F109: 12 | G109: Hair and make up
F110: 12.1 | G110: Hair and make up artist | K110: =H110*J110 -> 0 | N110: =K110-M110 -> 0
F111: 12.2 | G111: Hair and make up assistant | K111: =H111*J111 -> 0 | N111: =K111-M111 -> 0
...

Sheet Access Budget
B1: BFI and Film4 Future Takes: Access Budget
B2: Budget Breakdown | I2: Cost reporting
B3: Line No. | C3: Description | D3: Amounts | E3: Unit | F3: Rate (£) | G3: Subtotal | H3: Notes | I3: Actual | J3: Variance | K3: Notes
B4: Example: | D4: 5 | E4: Days | F4: 500 | G4: =D4*F4 -> 2500
C5: General Access Costs
G6: =F6*D6 -> 0 | J6: =G6-I6 -> 0
G7: =F7*D7 -> 0 | J7: =G7-I7 -> 0
G8: =F8*D8 -> 0 | J8: =G8-I8 -> 0
G9: =F9*D9 -> 0 | J9: =G9-I9 -> 0
G10: =F10*D10 -> 0 | J10: =G10-I10 -> 0
G11: =F11*D11 -> 0 | J11: =G11-I11 -> 0
G12: =F12*D12 -> 0 | J12: =G12-I12 -> 0
G13: =F13*D13 -> 0 | J13: =G13-I13 -> 0
G14: =F14*D14 -> 0 | J14: =G14-I14 -> 0
G15: =F15*D15 -> 0 | J15: =G15-I15 -> 0
B17: Subtotal: | G17: =SUM(G6:G16) -> 0 | I17: =SUM(I6:I16) -> 0 | J17: =SUM(J6:J16) -> 0
B18: Total general access costs: | H18: =G17 -> 0 | I18: =SUM(I9:I16) -> 0 | J18: =SUM(J17) -> 0
B20: 4 | C20: Cast
B21: 4.1 | C21: Casting director | G21: =D21*F21 -> 0 | J21: =G21-I21 -> 0
B22: 4.2 | C22: Lead cast
B23: 4.2.1 | C23: Lead actor / Voice over artist | G23: =D23*F23 -> 0 | J23: =G23-I23 -> 0
B24: 4.2.2 | C24: Lead actor 2 | G24: =D24*F24 -> 0 | J24: =G24-I24 -> 0
B25: 4.2.3 | C25: Lead actor 3 | G25: =D25*F25 -> 0 | J25: =G25-I25 -> 0
B26: 4.3 | C26: Supporting cast
B27: 4.3.1 | C27: Supporting actor 1 | G27: =D27*F27 -> 0 | J27: =G27-I27 -> 0
B28: 4.3.2 | C28: Supporting actor 2 | G28: =D28*F28 -> 0 | J28: =G28-I28 -> 0
B29: 4.3.3 | C29: Supporting actor 3 | G29: =D29*F29 -> 0 | J29: =G29-I29 -> 0
B30: 4.4 | C30: Extras
B31: 4.4.1 | C31: Scene number: | G31: =D31*F31 -> 0 | J31: =G31-I31 -> 0
B32: 4.4.2 | C32: Scene number: | G32: =D32*F32 -> 0 | J32: =G32-I32 -> 0
B33: 4.4.3 | C33: Scene number: | G33: =D33*F33 -> 0 | J33: =G33-I33 -> 0
B34: 4.5 | C34: Stunt coordinator | G34: =D34*F34 -> 0 | J34: =G34-I34 -> 0
B35: 4.6 | C35: Dialogue coach | G35: =D35*F35 -> 0 | J35: =G35-I35 -> 0
B36: 4.7 | C36: Chaperone | G36: =D36*F36 -> 0 | J36: =G36-I36 -> 0
B38: Subtotal: | G38: =SUM(G21:G37) -> 0 | I38: =SUM(I21:I37) -> 0 | J38: =SUM(J21:J37) -> 0
B39: 5 | C39: Production
B40: 5.1 | C40: Line producer | G40: =D40*F40 -> 0 | J40: =G40-I40 -> 0
B41: 5.2 | C41: Production manager | G41: =D41*F41 -> 0 | J41: =G41-I41 -> 0
B42: 5.3 | C42: Production coordinator | G42: =D42*F42 -> 0 | J42: =G42-I42 -> 0
B43: 5.4 | C43: Production assistant | G43: =D43*F43 -> 0 | J43: =G43-I43 -> 0
B44: 5.5 | C44: Production runner | G44: =D44*F44 -> 0 | J44: =G44-I44 -> 0
B45: 5.6 | C45: Location manager | G45: =D45*F45 -> 0 | J45: =G45-I45 -> 0
B46: 5.7 | C46: Script supervisor | G46: =D46*F46 -> 0 | J46: =G46-I46 -> 0
B48: Subtotal: | G48: =SUM(G40:G47) -> 0 | I48: =SUM(I40:I47) -> 0 | J48: =SUM(J40:J47) -> 0
B49: 6 | C49: Assistant Directors
B50: 6.1 | C50: First assistant director | G50: =D50*F50 -> 0 | J50: =G50-I50 -> 0
B51: 6.2 | C51: Second assistant director | G51: =D51*F51 -> 0 | J51: =G51-I51 -> 0
B52: 6.3 | C52: Third assistant director | G52: =D52*F52 -> 0 | J52: =G52-I52 -> 0
B53: 6.4 | C53: Floor runner 1 | G53: =D53*F53 -> 0 | J53: =G53-I53 -> 0
B54: 6.5 | C54: Floor runner 2 | G54: =D54*F54 -> 0 | J54: =G54-I54 -> 0
B56: Subtotal: | G56: =SUM(G50:G55) -> 0 | I56: =SUM(I50:I55) -> 0 | J56: =SUM(J50:J55) -> 0
B57: 7 | C57: Camera
B58: 7.1 | C58: Director of photography | G58: =D58*F58 -> 0 | J58: =G58-I58 -> 0
B59: 7.2 | C59: First assistant camera | G59: =D59*F59 -> 0 | J59: =G59-I59 -> 0
B60: 7.3 | C60: Second assistant camera | G60: =D60*F60 -> 0 | J60: =G60-I60 -> 0
B61: 7.4 | C61: Grip | G61: =D61*F61 -> 0 | J61: =G61-I61 -> 0
B62: 7.5 | C62: Digital imaging technician | G62: =D62*F62 -> 0 | J62: =G62-I62 -> 0
B63: 7.6 | C63: Camera package | G63: =D63*F63 -> 0 | J63: =G63-I63 -> 0
B65: Subtotal: | G65: =SUM(G58:G64) -> 0 | I65: =SUM(I58:I64) -> 0 | J65: =SUM(J58:J64) -> 0
B66: 8 | C66: Lighting
B67: 8.1 | C67: Gaffer | G67: =D67*F67 -> 0 | J67: =G67-I67 -> 0
B68: 8.2 | C68: Electrician 1 | G68: =D68*F68 -> 0 | J68: =G68-I68 -> 0
B69: 8.3 | C69: Electrician 2 | G69: =D69*F69 -> 0 | J69: =G69-I69 -> 0
B70: 8.4 | C70: Electrician 3 | G70: =D70*F70 -> 0 | J70: =G70-I70 -> 0
B71: 8.5 | C71: Lighting package | G71: =D71*F71 -> 0 | J71: =G71-I71 -> 0
B72: 8.6 | C72: Generator | G72: =D72*F72 -> 0 | J72: =G72-I72 -> 0
B73: 8.7 | C73: Consumables | G73: =D73*F73 -> 0 | J73: =G73-I73 -> 0
B75: Subtotal: | G75: =SUM(G67:G74) -> 0 | I75: =SUM(I67:I74) -> 0 | J75: =SUM(J67:J74) -> 0
B76: 9 | C76: Sound
B77: 9.1 | C77: Recordist/mixer | G77: =D77*F77 -> 0 | J77: =G77-I77 -> 0
B78: 9.2 | C78: Boom operator | G78: =D78*F78 -> 0 | J78: =G78-I78 -> 0
B79: 9.3 | C79: Sound package | G79: =D79*F79 -> 0 | J79: =G79-I79 -> 0
B80: 9.4 | C80: Radios | G80: =D80*F80 -> 0 | J80: =G80-I80 -> 0
B82: Subtotal: | G82: =SUM(G77:G81) -> 0 | I82: =SUM(I77:I81) -> 0 | J82: =SUM(J77:J81) -> 0
B83: 10 | C83: Production design
B84: 10.1 | C84: Production designer | G84: =D84*F84 -> 0 | J84: =G84-I84 -> 0
B85: 10.2 | C85: Art director | G85: =D85*F85 -> 0 | J85: =G85-I85 -> 0
B86: 10.3 | C86: Set decorator | G86: =D86*F86 -> 0 | J86: =G86-I86 -> 0
B87: 10.4 | C87: Art department assistant | G87: =D87*F87 -> 0 | J87: =G87-I87 -> 0
B88: 10.5 | C88: Standby art director | G88: =D88*F88 -> 0 | J88: =G88-I88 -> 0
B89: 10.6 | C89: Storyboard artist | G89: =D89*F89 -> 0 | J89: =G89-I89 -> 0
B90: 10.7 | C90: Prop master | G90: =D90*F90 -> 0 | J90: =G90-I90 -> 0
B91: 10.8 | C91: Rentals | G91: =D91*F91 -> 0 | J91: =G91-I91 -> 0
B92: 10.9 | C92: Construction | G92: =D92*F92 -> 0 | J92: =G92-I92 -> 0
B93: 10.1 | C93: Special effects supervisor | G93: =D93*F93 -> 0 | J93: =G93-I93 -> 0
B94: 10.11 | C94: Consumbables | G94: =D94*F94 -> 0 | J94: =G94-I94 -> 0
B95: 10.12 | C95: Animals/wrangler | G95: =D95*F95 -> 0 | J95: =G95-I95 -> 0
B96: 10.13 | C96: Action vehicles | G96: =D96*F96 -> 0 | J96: =G96-I96 -> 0
B98: Subtotal: | G98: =SUM(G84:G97) -> 0 | I98: =SUM(I84:I97) -> 0 | J98: =SUM(J84:J97) -> 0
B99: 11 | C99: Costume
B100: 11.1 | C100: Costume designer | G100: =D100*F100 -> 0 | J100: =G100-I100 -> 0
B101: 11.2 | C101: Costume supervisor | G101: =D101*F101 -> 0 | J101: =G101-I101 -> 0
B103: Subtotal: | G103: =SUM(G100:G102) -> 0 | I103: =SUM(I100:I102) -> 0 | J103: =SUM(J100:J102) -> 0
B104: 12 | C104: Hair and make up
B105: 14.1 | C105: Hair and make up artist | G105: =D105*F105 -> 0 | J105: =G105-I105 -> 0
B106: 14.2 | C106: Hair and make up assistant | G106: =D106*F106 -> 0 | J106: =G106-I106 -> 0
B107: 14.6 | C107: Box rental | G107: =D107*F107 -> 0 | J107: =G107-I107 -> 0
B109: Subtotal: | G109: =SUM(G105:G108) -> 0 | I109: =SUM(I105:I108) -> 0 | J109: =SUM(J105:J108) -> 0
B110: 13 | C110: Locations
B111: 13.1 | C111: Stage rental / Studio hire | G111: =D111*F111 -> 0 | J111: =G111-I111 -> 0
...

Sheet Top Sheet
B1: BFI NETWORK England Short Film Fund: Production Budget Top Sheet
B2: ='Production Budget'!B4 -> Project title: | C2: ='Production Budget'!C4 -> 0 | F2: ='Production Budget'!F3 -> Budget Breakdown | I2: ='Production Budget'!M3 -> Cost reporting
F3: ='Production Budget'!F4 -> Line No. | G3: ='Production Budget'!G4 -> Description | H3: ='Production Budget'!K4 -> Subtotal | I3: ='Production Budget'!M4 -> Actual | J3: ='Production Budget'!N4 -> Variance
F4: ='Production Budget'!F6 -> 1 | G4: ='Production Budget'!G6 -> Story and script | H4: ='Production Budget'!K10 -> 0 | I4: ='Production Budget'!M10 -> 0 | J4: ='Production Budget'!N10 -> 0
B5: ='Production Budget'!B22 -> Finance Plan | F5: ='Production Budget'!F11 -> 2 | G5: ='Production Budget'!G11 -> Producer | H5: ='Production Budget'!K15 -> 0 | I5: ='Production Budget'!M15 -> 0 | J5: ='Production Budget'!N15 -> 0
B6: ='Production Budget'!B23 -> Source | C6: ='Production Budget'!C23 -> Amount (£) | D6: ='Production Budget'!D23 -> Secured | F6: ='Production Budget'!F16 -> 3 | G6: ='Production Budget'!G16 -> Director | H6: ='Production Budget'!K19 -> 0 | I6: ='Production Budget'!M19 -> 0 | J6: ='Production Budget'!N19 -> 0
B7: ='Production Budget'!B24 -> Award Request Amount | C7: ='Production Budget'!C24 -> 0 | F7: ='Production Budget'!F20 -> Total above the line: | H7: =SUM(H4:H6) -> 0 | I7: =SUM(I4:I6) -> 0 | J7: =SUM(J4:J6) -> 0
B8: ='Production Budget'!B26 -> [e.g. Private investment] | C8: ='Production Budget'!C26 -> 0 | D8: ='Production Budget'!D26 -> [yes/no] | F8: ='Production Budget'!F22 -> 4 | G8: ='Production Budget'!G22 -> Cast | H8: ='Production Budget'!K40 -> 0 | I8: ='Production Budget'!M40 -> 0 | J8: ='Production Budget'!N40 -> 0
B9: ='Production Budget'!B28 -> 0 | C9: ='Production Budget'!C28 -> 0 | D9: ='Production Budget'!D28 -> [yes/no] | F9: ='Production Budget'!F41 -> 5 | G9: ='Production Budget'!G41 -> Production | H9: ='Production Budget'!K50 -> 0 | I9: ='Production Budget'!M50 -> 0 | J9: ='Production Budget'!N50 -> 0
B10: ='Production Budget'!B30 -> 0 | C10: ='Production Budget'!C30 -> 0 | D10: ='Production Budget'!D30 -> [yes/no] | F10: ='Production Budget'!#REF! -> #REF! | G10: ='Production Budget'!#REF! -> #REF! | H10: ='Production Budget'!#REF! -> #REF! | I10: ='Production Budget'!#REF! -> #REF! | J10: ='Production Budget'!#REF! -> #REF!
B11: ='Production Budget'!B32 -> 0 | C11: ='Production Budget'!C32 -> 0 | D11: ='Production Budget'!D32 -> [yes/no] | F11: ='Production Budget'!#REF! -> #REF! | G11: ='Production Budget'!#REF! -> #REF! | H11: ='Production Budget'!#REF! -> #REF! | I11: ='Production Budget'!#REF! -> #REF! | J11: ='Production Budget'!#REF! -> #REF!
B12: ='Production Budget'!B34 -> Total finance plan | C12: ='Production Budget'!C34 -> 0 | F12: ='Production Budget'!F51 -> 6 | G12: ='Production Budget'!G51 -> Assistant Directors | H12: ='Production Budget'!K58 -> 0 | I12: ='Production Budget'!M58 -> 0 | J12: ='Production Budget'!N58 -> 0
B13: ='Production Budget'!B36 -> Total project budget | C13: ='Production Budget'!C36 -> 0 | F13: ='Production Budget'!F59 -> 7 | G13: ='Production Budget'!G59 -> Camera | H13: ='Production Budget'!K68 -> 0 | I13: ='Production Budget'!M68 -> 0 | J13: ='Production Budget'!N68 -> 0
B14: ='Production Budget'!B38 -> Budget surplus/deficit | C14: ='Production Budget'!C38 -> 0 | F14: ='Production Budget'!F69 -> 8 | G14: ='Production Budget'!G69 -> Lighting | H14: ='Production Budget'!K79 -> 0 | I14: ='Production Budget'!M79 -> 0 | J14: ='Production Budget'!N79 -> 0
B15: ='Production Budget'!B40 -> In kind support | F15: ='Production Budget'!F80 -> 9 | G15: ='Production Budget'!G80 -> Sound | H15: ='Production Budget'!K86 -> 0 | I15: ='Production Budget'!M86 -> 0 | J15: ='Production Budget'!N86 -> 0
B16: ='Production Budget'!B41 -> Source | C16: ='Production Budget'!C41 -> Amount (£) | D16: ='Production Budget'!D41 -> Secured | F16: ='Production Budget'!F87 -> 10 | G16: ='Production Budget'!G87 -> Production design | H16: ='Production Budget'!K102 -> 0 | I16: ='Production Budget'!M102 -> 0 | J16: ='Production Budget'!N102 -> 0
B17: ='Production Budget'!B42 -> [Organisation Name] | C17: ='Production Budget'!C42 -> 0 | D17: ='Production Budget'!D42 -> [yes/no] | F17: ='Production Budget'!F103 -> 11 | G17: ='Production Budget'!G103 -> Costume | H17: ='Production Budget'!K108 -> 0 | I17: ='Production Budget'!M108 -> 0 | J17: ='Production Budget'!N108 -> 0
B18: ='Production Budget'!B44 -> 0 | C18: ='Production Budget'!C44 -> 0 | D18: ='Production Budget'!D44 -> [yes/no] | F18: ='Production Budget'!F109 -> 12 | G18: ='Production Budget'!G109 -> Hair and make up | H18: ='Production Budget'!K117 -> 0 | I18: ='Production Budget'!M117 -> 0 | J18: ='Production Budget'!N117 -> 0
B19: ='Production Budget'!B46 -> 0 | C19: ='Production Budget'!C46 -> 0 | D19: ='Production Budget'!D46 -> [yes/no] | F19: ='Production Budget'!F118 -> 13 | G19: ='Production Budget'!G118 -> Locations | H19: ='Production Budget'!K131 -> 0 | I19: ='Production Budget'!M131 -> 0 | J19: ='Production Budget'!N131 -> 0
B20: Total in kind support | C20: ='Production Budget'!C48 -> 0 | F20: ='Production Budget'!F132 -> 14 | G20: ='Production Budget'!G132 -> Travel and transport | H20: ='Production Budget'!K144 -> 0 | I20: ='Production Budget'!M144 -> 0 | J20: ='Production Budget'!N144 -> 0
F21: ='Production Budget'!F145 -> 15 | G21: ='Production Budget'!G145 -> Accomodation | H21: ='Production Budget'!K150 -> 0 | I21: ='Production Budget'!M150 -> 0 | J21: ='Production Budget'!N150 -> 0
F22: ='Production Budget'!F151 -> 16 | G22: ='Production Budget'!G151 -> Post picture | H22: ='Production Budget'!K164 -> 0 | I22: ='Production Budget'!M164 -> 0 | J22: ='Production Budget'!N164 -> 0
F23: ='Production Budget'!F165 -> 17 | G23: ='Production Budget'!G165 -> Post sound | H23: ='Production Budget'!K172 -> 0 | I23: ='Production Budget'!M172 -> 0 | J23: ='Production Budget'!N172 -> 0
F24: ='Production Budget'!F173 -> 18 | G24: ='Production Budget'!G173 -> Music | H24: ='Production Budget'!K178 -> 0 | I24: ='Production Budget'!M178 -> 0 | J24: ='Production Budget'!N178 -> 0
F25: ='Production Budget'!F179 -> 19 | G25: ='Production Budget'!G179 -> Publicity | H25: ='Production Budget'!K186 -> 0 | I25: ='Production Budget'!M186 -> 0 | J25: ='Production Budget'!N186 -> 0
F26: ='Production Budget'!F187 -> 20 | G26: ='Production Budget'!G187 -> Miscellaneous | H26: ='Production Budget'!K200 -> 0 | I26: ='Production Budget'!M200 -> 0 | J26: ='Production Budget'!N200 -> 0
F27: ='Production Budget'!F201 -> Total below the line: | H27: =SUM(H8:H26) -> #REF! | I27: =SUM(I8:I26) -> #REF! | J27: =SUM(J8:J26) -> #REF!
F28: ='Production Budget'!F203 -> 21 | G28: ='Production Budget'!G203 -> Insurance | H28: ='Production Budget'!K206 -> 0 | I28: ='Production Budget'!M206 -> 0 | J28: ='Production Budget'!N206 -> 0
F29: ='Production Budget'!F207 -> 22 | G29: ='Production Budget'!G207 -> Contingency | H29: ='Production Budget'!K210 -> 0 | I29: ='Production Budget'!M210 -> 0 | J29: ='Production Budget'!N210 -> 0
F30: ='Production Budget'!F211 -> Total other: | H30: =SUM(H28:H29) -> 0 | I30: =SUM(I28:I29) -> 0 | J30: =SUM(J28:J29) -> 0
F32: Budget Total: | I32: =SUM(H30,H27,H7) -> #REF!
F33: Total Costs: | I33: =I30+I27+I7 -> #REF!
F34: Final Variance: | I34: =J30+J27+J7 -> #REF!
